odoo/addons/purchase_packaging_level_qty/README.rst
odoo/addons/purchase_packaging_level_qty/__init__.py
odoo/addons/purchase_packaging_level_qty/__manifest__.py
odoo/addons/purchase_packaging_level_qty/i18n/es.po
odoo/addons/purchase_packaging_level_qty/i18n/it.po
odoo/addons/purchase_packaging_level_qty/i18n/purchase_packaging_level_qty.pot
odoo/addons/purchase_packaging_level_qty/models/__init__.py
odoo/addons/purchase_packaging_level_qty/models/purchase_order.py
odoo/addons/purchase_packaging_level_qty/models/purchase_order_line.py
odoo/addons/purchase_packaging_level_qty/models/res_company.py
odoo/addons/purchase_packaging_level_qty/models/res_config_settings.py
odoo/addons/purchase_packaging_level_qty/readme/CONTRIBUTORS.rst
odoo/addons/purchase_packaging_level_qty/readme/DESCRIPTION.rst
odoo/addons/purchase_packaging_level_qty/readme/USAGE.rst
odoo/addons/purchase_packaging_level_qty/static/description/icon.png
odoo/addons/purchase_packaging_level_qty/static/description/index.html
odoo/addons/purchase_packaging_level_qty/tests/__init__.py
odoo/addons/purchase_packaging_level_qty/tests/test_purchase_packaging_level_qty.py
odoo/addons/purchase_packaging_level_qty/views/purchase_order_view.xml
odoo/addons/purchase_packaging_level_qty/views/res_config_settings_views.xml
odoo_addon_purchase_packaging_level_qty-16.0.2.0.0.2.dist-info/METADATA
odoo_addon_purchase_packaging_level_qty-16.0.2.0.0.2.dist-info/WHEEL
odoo_addon_purchase_packaging_level_qty-16.0.2.0.0.2.dist-info/top_level.txt
odoo_addon_purchase_packaging_level_qty-16.0.2.0.0.2.dist-info/RECORD
