Metadata-Version: 2.1
Name: odoo-addon-purchase_packaging_level_qty
Version: 16.0.2.0.0.2
Summary: Display purchase order packaging level quantity
Home-page: https://github.com/OCA/purchase-workflow
Author: Camptocamp, BCIM, Odoo Community Association (OCA)
Author-email: support@odoo-community.org
License: AGPL-3
Classifier: Programming Language :: Python
Classifier: Framework :: Odoo
Classifier: Framework :: Odoo :: 16.0
Classifier: License :: OSI Approved :: GNU Affero General Public License v3
Requires-Python: >=3.10
Requires-Dist: odoo-addon-product-packaging-level<16.1dev,>=16.0dev
Requires-Dist: odoo<16.1dev,>=16.0a
